[{"sg":"1.94","time":0},{"sg":"1.80","time":1},{"sg":"1.25","time":2},{"sg":"0.49","time":3},{"sg":"-0.36","time":4},{"sg":"-1.08","time":5},{"sg":"-1.51","time":6},{"sg":"-1.54","time":7},{"sg":"-1.18","time":8},{"sg":"-0.56","time":9},{"sg":"0.20","time":10},{"sg":"0.85","time":11},{"sg":"1.21","time":12},{"sg":"1.21","time":13},{"sg":"0.85","time":14},{"sg":"0.23","time":15},{"sg":"-0.52","time":16},{"sg":"-1.15","time":17},{"sg":"-1.54","time":18},{"sg":"-1.61","time":19},{"sg":"-1.25","time":20},{"sg":"-0.59","time":21},{"sg":"0.23","time":22},{"sg":"1.02","time":23},{"sg":"1.61","time":24},{"sg":"1.80","time":1},{"sg":"1.61","time":2},{"sg":"1.08","time":3},{"sg":"0.36","time":4},{"sg":"-0.43","time":5},{"sg":"-1.02","time":6},{"sg":"-1.38","time":7},{"sg":"-1.38","time":8},{"sg":"-1.05","time":9},{"sg":"-0.46","time":10},{"sg":"0.20","time":11},{"sg":"0.75","time":12},{"sg":"1.05","time":13},{"sg":"1.02","time":14},{"sg":"0.66","time":15},{"sg":"0.07","time":16},{"sg":"-0.59","time":17},{"sg":"-1.15","time":18},{"sg":"-1.44","time":19},{"sg":"-1.44","time":20},{"sg":"-1.08","time":21},{"sg":"-0.46","time":22},{"sg":"0.30","time":23},{"sg":"1.05","time":0},{"sg":"1.57","time":1},{"sg":"1.74","time":2},{"sg":"1.54","time":3},{"sg":"1.02","time":4},{"sg":"0.33","time":5},{"sg":"-0.39","time":6},{"sg":"-0.98","time":7},{"sg":"-1.28","time":8},{"sg":"-1.31","time":9},{"sg":"-0.98","time":10},{"sg":"-0.46","time":11},{"sg":"0.16","time":12},{"sg":"0.72","time":13},{"sg":"0.98","time":14},{"sg":"0.92","time":15},{"sg":"0.56","time":16},{"sg":"0.00","time":17},{"sg":"-0.59","time":18},{"sg":"-1.12","time":19},{"sg":"-1.41","time":20},{"sg":"-1.41","time":21},{"sg":"-1.08","time":22},{"sg":"-0.46","time":23},{"sg":"0.33","time":0},{"sg":"1.08","time":1},{"sg":"1.61","time":2},{"sg":"1.77","time":3},{"sg":"1.54","time":4},{"sg":"1.02","time":5},{"sg":"0.33","time":6},{"sg":"-0.36","time":7},{"sg":"-0.98","time":8},{"sg":"-1.31","time":9},{"sg":"-1.35","time":10},{"sg":"-1.05","time":11},{"sg":"-0.49","time":12},{"sg":"0.20","time":13},{"sg":"0.75","time":14},{"sg":"1.05","time":15},{"sg":"0.98","time":16},{"sg":"0.62","time":17},{"sg":"0.03","time":18},{"sg":"-0.59","time":19},{"sg":"-1.12","time":20},{"sg":"-1.48","time":21},{"sg":"-1.48","time":22},{"sg":"-1.15","time":23},{"sg":"-0.49","time":0}]